roadtools/roadlib/__init__.py
roadtools/roadlib/asyncauth.py
roadtools/roadlib/asyncdeviceauth.py
roadtools/roadlib/auth.py
roadtools/roadlib/constants.py
roadtools/roadlib/dbgen.py
roadtools/roadlib/dbgen_msgraph.py
roadtools/roadlib/deviceauth.py
roadtools/roadlib/metagen.py
roadtools/roadlib/metagen_msgraph.py
roadtools/roadlib/wstrust.py
roadtools/roadlib/metadef/__init__.py
roadtools/roadlib/metadef/basetypes.py
roadtools/roadlib/metadef/complextypes.py
roadtools/roadlib/metadef/complextypes_msgraph.py
roadtools/roadlib/metadef/database.py
roadtools/roadlib/metadef/database_msgraph.py
roadtools/roadlib/metadef/entitytypes.py
roadtools/roadlib/metadef/entitytypes_msgraph.py
roadlib-1.5.0.dist-info/METADATA
roadlib-1.5.0.dist-info/WHEEL
roadlib-1.5.0.dist-info/top_level.txt
roadlib-1.5.0.dist-info/RECORD
