Metadata-Version: 2.4
Name: roadlib
Version: 1.5.0
Summary: ROADtools common components library
Home-page: https://github.com/dirkjanm/ROADtools/
Author: Dirk-jan Mollema
Author-email: dirkjan@outsidersecurity.nl
License: MIT
Classifier: Intended Audience :: Information Technology
Classifier: Programming Language :: Python :: 3
Classifier: Programming Language :: Python :: 3.9
Classifier: Programming Language :: Python :: 3.10
Classifier: Programming Language :: Python :: 3.11
Classifier: Programming Language :: Python :: 3.12
Classifier: Programming Language :: Python :: 3.13
Requires-Dist: requests
Requires-Dist: cryptography
Requires-Dist: sqlalchemy>=1.4
Requires-Dist: pyjwt>=2.0
Provides-Extra: async
Requires-Dist: aiohttp; extra == "async"
Dynamic: author
Dynamic: author-email
Dynamic: classifier
Dynamic: home-page
Dynamic: license
Dynamic: provides-extra
Dynamic: requires-dist
Dynamic: summary
